Metadata-Version: 1.0
Name: distributions-gauussbinom
Version: 0.1
Summary: Gaussian distributions
Home-page: UNKNOWN
Author: Sandeep Solanki
Author-email: UNKNOWN
License: UNKNOWN
Platform: UNKNOWN
